django_min_custom_user/__init__.py
django_min_custom_user/admin.py
django_min_custom_user/apps.py
django_min_custom_user/manager.py
django_min_custom_user/migrations/__init__.py
django_min_custom_user/models.py
django_min_custom_user-0.2.0.dist-info/LICENSE
django_min_custom_user-0.2.0.dist-info/METADATA
django_min_custom_user-0.2.0.dist-info/WHEEL
django_min_custom_user-0.2.0.dist-info/RECORD
