Metadata-Version: 2.1
Name: django-min-custom-user
Version: 0.2.0
Summary: A project with a mininum fields Django Custom User
License: MIT
Author: Renzo Nuccitelli
Author-email: renzo.n@gmail.com
Requires-Python: >=3.12,<4.0
Classifier: License :: OSI Approved :: MIT License
Classifier: Programming Language :: Python :: 3
Classifier: Programming Language :: Python :: 3.12
Requires-Dist: django (>=5.0.7,<6.0.0)
